MANIFEST.in
setup.py
assnake_core_preprocessing/__init__.py
assnake_core_preprocessing/snake_module_setup.py
assnake_core_preprocessing/utils.py
assnake_core_preprocessing.egg-info/PKG-INFO
assnake_core_preprocessing.egg-info/SOURCES.txt
assnake_core_preprocessing.egg-info/dependency_links.txt
assnake_core_preprocessing.egg-info/entry_points.txt
assnake_core_preprocessing.egg-info/requires.txt
assnake_core_preprocessing.egg-info/top_level.txt
assnake_core_preprocessing/__pycache__/__init__.cpython-36.pyc
assnake_core_preprocessing/__pycache__/snake_module_setup.cpython-36.pyc
assnake_core_preprocessing/count/__init__.py
assnake_core_preprocessing/count/count.result.json
assnake_core_preprocessing/count/result.py
assnake_core_preprocessing/count/wc_config.yaml
assnake_core_preprocessing/count/workflow.smk
assnake_core_preprocessing/count/__pycache__/__init__.cpython-36.pyc
assnake_core_preprocessing/count/__pycache__/cmd_count.cpython-36.pyc
assnake_core_preprocessing/count/__pycache__/result.cpython-36.pyc
assnake_core_preprocessing/count/scripts/count_bp.sh
assnake_core_preprocessing/fastq_dump/download.py
assnake_core_preprocessing/fastq_dump/env.yaml
assnake_core_preprocessing/fastqc/__init__.py
assnake_core_preprocessing/fastqc/env_v0.11.8.yaml
assnake_core_preprocessing/fastqc/fastqc.json
assnake_core_preprocessing/fastqc/result_fastqc.py
assnake_core_preprocessing/fastqc/wc_config.yaml
assnake_core_preprocessing/fastqc/workflow.smk
assnake_core_preprocessing/fastqc/wrapper.py
assnake_core_preprocessing/fastqc/__pycache__/__init__.cpython-36.pyc
assnake_core_preprocessing/fastqc/__pycache__/cmd_fastqc.cpython-36.pyc
assnake_core_preprocessing/fastqc/__pycache__/result_fastqc.cpython-36.pyc
assnake_core_preprocessing/minlen/minlen_bbmap.py
assnake_core_preprocessing/multiqc/__init__.py
assnake_core_preprocessing/multiqc/cmd_multiqc.py
assnake_core_preprocessing/multiqc/multiqc.py
assnake_core_preprocessing/multiqc/multiqc.yaml
assnake_core_preprocessing/multiqc/result.py
assnake_core_preprocessing/multiqc/wc_config.yaml
assnake_core_preprocessing/multiqc/workflow.smk
assnake_core_preprocessing/multiqc/__pycache__/__init__.cpython-36.pyc
assnake_core_preprocessing/multiqc/__pycache__/cmd_multiqc.cpython-36.pyc
