Metadata-Version: 1.0
Name: assnake-core-preprocessing
Version: 0.5.1
Summary: Reads preprocessing module for assnake
Home-page: https://github.com/ASSNAKE/assnake-core-preprocessing
Author: Dmitry Fedorov
Author-email: fedorov.de@gmail.com
License: MIT
Keywords: ILLUMINA,NGS,METAGENOMIC,DATA
Platform: UNKNOWN
